bigquery_view_analyzer/__init__.py
bigquery_view_analyzer/analyzer.py
bigquery_view_analyzer/cli.py
bigquery_view_analyzer-20.4.1.dist-info/LICENSE
bigquery_view_analyzer-20.4.1.dist-info/METADATA
bigquery_view_analyzer-20.4.1.dist-info/WHEEL
bigquery_view_analyzer-20.4.1.dist-info/entry_points.txt
bigquery_view_analyzer-20.4.1.dist-info/top_level.txt
bigquery_view_analyzer-20.4.1.dist-info/RECORD
