Metadata-Version: 2.1
Name: bigquery-view-analyzer
Version: 20.4.1
Summary: A command-line tool for visualizing dependencies and managing permissions between BigQuery views
Home-page: http://github.com/servian/bigquery-view-analyzer/
Author: Chris Tippett
Author-email: chris.tippett@servian.com
License: MIT
Platform: UNKNOWN
Classifier: Programming Language :: Python
Classifier: Programming Language :: Python :: 3.6
Classifier: Programming Language :: Python :: 3.7
Classifier: License :: OSI Approved :: MIT License
Classifier: Operating System :: OS Independent
Classifier: Topic :: Software Development :: Libraries
Classifier: Topic :: Utilities
Requires-Dist: google-cloud-bigquery (>=1.23)
Requires-Dist: six (<2.0.0dev,>=1.13.0)
Requires-Dist: anytree (==2.8.0)
Requires-Dist: colorama (==0.4.3)
Requires-Dist: yaspin (==0.16.0)
Requires-Dist: Click (==7.0)
